fireflask.py
fireflask-0.2.0.dist-info/DESCRIPTION.rst
fireflask-0.2.0.dist-info/METADATA
fireflask-0.2.0.dist-info/metadata.json
fireflask-0.2.0.dist-info/RECORD
fireflask-0.2.0.dist-info/top_level.txt
fireflask-0.2.0.dist-info/WHEEL
