Metadata-Version: 2.0
Name: fireflask
Version: 0.2.0
Summary: Simple, beautiful logging from Flask web apps to FireBug console
Home-page: https://bitbucket.org/jeunice/fireflask
Author: Jonathan Eunice
Author-email: jonathan.eunice@gmail.com
License: Apache License 2.0
Keywords: webapp Flask debug log logging FireBug FireLogger FirePython
Platform: UNKNOWN
Classifier: Development Status :: 4 - Beta
Classifier: Operating System :: OS Independent
Classifier: License :: OSI Approved :: Apache Software License
Classifier: Intended Audience :: Developers
Classifier: Programming Language :: Python
Classifier: Programming Language :: Python :: 2.6
Classifier: Programming Language :: Python :: 2.7
Classifier: Programming Language :: Python :: Implementation :: CPython
Classifier: Topic :: Software Development :: Debuggers
Classifier: Topic :: Software Development :: Libraries :: Python Modules
Classifier: Framework :: Flask
Classifier: Environment :: Web Environment
Requires-Dist: firepython (>=0.9)
Requires-Dist: flask
